dresden/__init__.py
dresden/dresden.py
dresden/exceptions.py
dresden/models.py
dresden/py.typed
dresden-1.0.0.dist-info/LICENSE
dresden-1.0.0.dist-info/METADATA
dresden-1.0.0.dist-info/WHEEL
dresden-1.0.0.dist-info/RECORD
