Metadata-Version: 2.1
Name: dresden
Version: 1.0.0
Summary: Asynchronous Python client providing Open Data information of dresden
Home-page: https://github.com/klaasnicolaas/python-dresden
License: MIT
Keywords: data,platform,dresden,parking,api,async,client
Author: Klaas Schoute
Author-email: hello@student-techlife.com
Maintainer: Klaas Schoute
Maintainer-email: hello@student-techlife.com
Requires-Python: >=3.11,<4.0
Classifier: Framework :: AsyncIO
Classifier: Intended Audience :: Developers
Classifier: License :: OSI Approved :: MIT License
Classifier: Natural Language :: English
Classifier: Programming Language :: Python :: 3
Classifier: Programming Language :: Python :: 3.11
Classifier: Programming Language :: Python :: 3.12
Classifier: Programming Language :: Python :: 3.13
Classifier: Topic :: Software Development :: Libraries :: Python Modules
Requires-Dist: aiohttp (>=3.0.0)
Requires-Dist: pytz (>=2024.2,<2024.3)
Requires-Dist: yarl (>=1.6.0)
Project-URL: Bug Tracker, https://github.com/klaasnicolaas/python-dresden/issues
Project-URL: Changelog, https://github.com/klaasnicolaas/python-dresden/releases
Project-URL: Documentation, https://github.com/klaasnicolaas/python-dresden
Project-URL: Repository, https://github.com/klaasnicolaas/python-dresden
